wapl/__init__.py
wapl/wapl.py
wapl-0.0.3.dist-info/LICENSE
wapl-0.0.3.dist-info/METADATA
wapl-0.0.3.dist-info/WHEEL
wapl-0.0.3.dist-info/top_level.txt
wapl-0.0.3.dist-info/RECORD
