Metadata-Version: 2.1
Name: wapl
Version: 0.0.3
Summary: TMAX WAPL testing package
Home-page: https://github.com/ZeroStrength/wapl
Author: Changyun Lee
Author-email: brownbearpower@gmail.com
License: UNKNOWN
Platform: UNKNOWN
Classifier: Programming Language :: Python :: 3
Classifier: License :: OSI Approved :: MIT License
Classifier: Operating System :: OS Independent
Requires-Python: >=3.6
Requires-Dist: selenium
